MANIFEST.in
README.txt
setup.cfg
setup.py
docs/HISTORY.txt
docs/INSTALL.txt
docs/LICENSE.GPL
docs/LICENSE.txt
jalon/__init__.py
jalon.intracursus.egg-info/PKG-INFO
jalon.intracursus.egg-info/SOURCES.txt
jalon.intracursus.egg-info/dependency_links.txt
jalon.intracursus.egg-info/entry_points.txt
jalon.intracursus.egg-info/namespace_packages.txt
jalon.intracursus.egg-info/not-zip-safe
jalon.intracursus.egg-info/paster_plugins.txt
jalon.intracursus.egg-info/requires.txt
jalon.intracursus.egg-info/top_level.txt
jalon/intracursus/__init__.py
jalon/intracursus/configure.zcml
jalon/intracursus/skins.zcml
jalon/intracursus/tests.py
jalon/intracursus/browser/__init__.py
jalon/intracursus/browser/configure.zcml
jalon/intracursus/browser/interfaces.py
jalon/intracursus/browser/scripts/__init__.py
jalon/intracursus/browser/scripts/connecteur_intracursus.py
jalon/intracursus/browser/templates/jalon_connecteur_intracursus.pt
jalon/intracursus/content/__init__.py
jalon/intracursus/content/configure.zcml
jalon/intracursus/content/interfaces.py
jalon/intracursus/content/jalon_intracursus.py
jalon/intracursus/profiles/default/componentregistry.xml
jalon/intracursus/profiles/default/controlpanel.xml
jalon/intracursus/profiles/default/metadata.xml
jalon/intracursus/profiles/default/skins.xml
jalon/intracursus/profiles/default/toolset.xml
jalon/intracursus/skins/jalon_intracursus/creationPresenceIntracursus.py
jalon/intracursus/skins/jalon_intracursus/creationSeanceIntracursus.py
jalon/intracursus/skins/jalon_intracursus/informationSeanceIntracursus.py
jalon/intracursus/skins/jalon_intracursus/listerEtudiantSeanceIntracursus.py
jalon/intracursus/skins/jalon_intracursus/listerSeanceIntracursus.py
jalon/intracursus/skins/jalon_intracursus/modificationSeanceIntracursus.py
jalon/intracursus/skins/jalon_intracursus/nombreSeanceIntracursus.py
jalon/intracursus/skins/jalon_intracursus/publicationSeanceIntracursus.py
jalon/intracursus/skins/jalon_intracursus/saveVariablesIntracursus.py
jalon/intracursus/skins/jalon_intracursus/suppressionSeanceIntracursus.py
jalon/intracursus/skins/jalon_intracursus/testerConnexionIntracursus.py